{"classifier":{"examples":{},"features":[],"featurePositions":{},"maxFeaturePosition":0,"classifications":[],"exampleCount":0},"docs":[{"label":"Greetings","text":["hello"]},{"label":"Greetings","text":["hi"]},{"label":"Greetings","text":["hiii"]},{"label":"Greetings","text":["hei"]},{"label":"Opening","text":["open","time"]},{"label":"Opening","text":["open"]},{"label":"Opening","text":["close"]},{"label":"Opening","text":["close"]},{"label":"Opening","text":["hour"]},{"label":"Opening","text":["work","hour"]},{"label":"Opening","text":["time"]},{"label":"Opening","text":["hour","swing"]},{"label":"Opening","text":["tell","late","store","open","till"]},{"label":"Opening","text":["earli","open"]},{"label":"Opening","text":["long","open"]},{"label":"Opening","text":["long","open"]},{"label":"Anger","text":["stop"]},{"label":"Anger","text":["rude"]},{"label":"Okay","text":["ok"]},{"label":"Okay","text":["cool"]},{"label":"Okay","text":["okai"]},{"label":"Okay","text":["okai"]},{"label":"Okay","text":["fine"]},{"label":"Okay","text":["nice"]},{"label":"Okay","text":["ehum"]},{"label":"Okay","text":["alright"]},{"label":"Okay","text":["alright"]},{"label":"Okay","text":["great"]},{"label":"Okay","text":["good","know"]},{"label":"Thanks","text":["thank"]},{"label":"Thanks","text":["thank"]},{"label":"Thanks","text":["appreci"]},{"label":"Thanks","text":["appreci"]},{"label":"Thanks","text":["love"]},{"label":"Thanks","text":["love"]},{"label":"Thanks","text":["love"]},{"label":"Thanks","text":["affirm","look"]},{"label":"Thanks","text":["right"]},{"label":"Thanks","text":["great"]},{"label":"Thanks","text":["sweet"]},{"label":"Thanks","text":["look"]},{"label":"Bye","text":["bye"]},{"label":"Bye","text":["soon"]},{"label":"Bye","text":["la","prochain"]},{"label":"Bye","text":["leav"]},{"label":"Confirmation","text":["realli"]},{"label":"Confirmation","text":["seriou"]},{"label":"Confirmation","text":["sure"]},{"label":"Name","text":["name"]},{"label":"Name","text":["purpos"]},{"label":"Name","text":["tell"]},{"label":"Name","text":["know"]},{"label":"Name","text":["mission"]},{"label":"No","text":["no"]},{"label":"No","text":["don"]},{"label":"No","text":["nevermind"]},{"label":"explanation","text":["exampl"]},{"label":"explanation","text":["explain"]},{"label":"Operation numerique","text":["calcul"]},{"label":"Operation numerique","text":["plu"]},{"label":"Operation numerique","text":["minu"]},{"label":"Operation numerique","text":["result","oper"]},{"label":"Google search","text":["search"]},{"label":"Google search","text":["search"]},{"label":"Google search","text":["search","internet"]},{"label":"Google search","text":["googl"]},{"label":"Google search","text":["googl"]},{"label":"Google search","text":["googl"]},{"label":"Google search","text":["wikepedia"]},{"label":"Google search","text":["definit"]},{"label":"Google search","text":["look","internet"]},{"label":"Google search","text":["look"]},{"label":"Google search","text":["find"]},{"label":"Google search","text":["lookup"]},{"label":"Joke","text":["tell","joke"]},{"label":"Joke","text":["funni"]},{"label":"Joke","text":["laugh"]},{"label":"Joke","text":["haha"]},{"label":"Joke","text":["show","sens","humour"]},{"label":"smallTalk","text":["okai"]},{"label":"login","text":["login"]},{"label":"login","text":["authent"]},{"label":"login","text":["access","insur"]},{"label":"login","text":["access","profil"]},{"label":"statusClaim","text":["check","statu","claim"]},{"label":"statusClaim","text":["check","statu"]},{"label":"statusClaim","text":["chack","statu","insur","claim"]},{"label":"statusClaim","text":["tell","progress","case"]},{"label":"statusClaim","text":["claim","proce"]},{"label":"statusClaim","text":["give","info","current","claim"]},{"label":"statusClaim","text":["decis","reach"]},{"label":"statusClaim","text":["help","know","updat","claim"]},{"label":"statusClaim","text":["check","car","accid","claim","statu","onlin"]},{"label":"statusClaim","text":["need","monei","immedi","approv","quickli"]},{"label":"statusClaim","text":["possibl","know","progress","insur","claim"]},{"label":"statusClaim","text":["new","inform","claim"]},{"label":"statusClaim","text":["know","claim","reject"]},{"label":"statusClaim","text":["statu","pend","week"]},{"label":"statusClaim","text":["date","approv"]},{"label":"statusClaim","text":["progress","claim"]},{"label":"statusClaim","text":["monei"]},{"label":"statusClaim","text":["claim","gonna","process"]},{"label":"statusClaim","text":["claim","approv"]},{"label":"statusClaim","text":["monei"]},{"label":"statusClaim","text":["inform","need","provid","check","claim","statu"]},{"label":"statusClaim","text":["inform","need","provid","check","claim","progress"]},{"label":"statusClaim","text":["possibl","know","claim","statu","call"]},{"label":"fileClaim","text":["add","claim"]},{"label":"fileClaim","text":["file","claim"]},{"label":"fileClaim","text":["claim"]},{"label":"fileClaim","text":["file","claim","car","damag","accid"]},{"label":"fileClaim","text":["car","damag","accid"]},{"label":"fileClaim","text":["want","know","claim","file"]},{"label":"fileClaim","text":["know","claim","file"]},{"label":"fileClaim","text":["process","file","claim"]},{"label":"fileClaim","text":["done","file","claim"]},{"label":"register","text":["new"]},{"label":"register","text":["show","regist","program"]},{"label":"register","text":["explain","creat","fresh","account"]},{"label":"register","text":["regist"]},{"label":"register","text":["becom","custom"]},{"label":"register","text":["regist"]},{"label":"register","text":["account"]},{"label":"register","text":["pleas","tell","regist","on","member"]},{"label":"register","text":["need","start","account"]},{"label":"register","text":["requir","sign"]},{"label":"register","text":["log","process","new","user"]},{"label":"register","text":["process","make","account"]},{"label":"register","text":["regist"]},{"label":"assistanceChoice","text":["option"]},{"label":"assistanceChoice","text":["hesit"]},{"label":"assistanceChoice","text":["don","know","ask"]},{"label":"assistanceChoice","text":["don","know"]},{"label":"payementStatus","text":["payement","statu"]},{"label":"payementStatus","text":["paiement","statu"]},{"label":"payementStatus","text":["check","payement"]},{"label":"payementStatus","text":["payement","due"]},{"label":"payementStatus","text":["ask","payement"]},{"label":"payementStatus","text":["ask","paiement"]},{"label":"payementStatus","text":["need","pai","servic"]},{"label":"payementStatus","text":["pai"]},{"label":"pay","text":["go","pai"]},{"label":"pay","text":["want","pai","insur"]},{"label":"pay","text":["want","pai","servic"]},{"label":"pay","text":["help","transfer","monei","servic"]},{"label":"pay","text":["transfer","fund","electron"]},{"label":"pay","text":["pleas","assist","transfer","fund"]},{"label":"pay","text":["transfer","monei","insur"]},{"label":"pay","text":["bill","payment"]},{"label":"pay","text":["pai","bill"]},{"label":"pay","text":["assist","pai","bill"]},{"label":"pay","text":["pai"]},{"label":"pay","text":["think","gonna","pai","bill"]},{"label":"pay","text":["need","pai","cost","servic","plan"]},{"label":"pay","text":["want","pai"]},{"label":"pay","text":["accept","paypal"]},{"label":"policyInquiry","text":["want","polici","estim"]},{"label":"policyInquiry","text":["want","estim","insur","polici"]},{"label":"policyInquiry","text":["cost","car","coverag"]},{"label":"policyInquiry","text":["cover","car","accid"]},{"label":"policyInquiry","text":["cost","car","accid","coverag"]},{"label":"cancel","text":["cancel"]},{"label":"cancel","text":["exit"]},{"label":"cancel","text":["backup"]},{"label":"cancel","text":["back"]},{"label":"cancel","text":["go","back","on","step"]},{"label":"cancel","text":["chang","mind"]},{"label":"cancel","text":["nevermind"]},{"label":"prediction","text":["suggest","type","insur"]},{"label":"prediction","text":["help","pick","insur","type"]},{"label":"prediction","text":["help","go","process","pick","insur","type"]},{"label":"prediction","text":["best","insur","deal"]},{"label":"prediction","text":["pick","best","insur","type","situat"]},{"label":"subscribe","text":["subscrib","option"]},{"label":"subscribe","text":["confirm","subscript"]},{"label":"scoreAnalysis","text":["score","analysi"]},{"label":"scoreAnalysis","text":["mood"]}],"features":{"hello":1,"hi":1,"hiii":1,"hei":1,"open":6,"time":2,"close":2,"hour":3,"work":1,"swing":1,"tell":5,"late":1,"store":1,"till":1,"earli":1,"long":2,"stop":1,"rude":1,"ok":1,"cool":1,"okai":3,"fine":1,"nice":1,"ehum":1,"alright":2,"great":2,"good":1,"know":10,"thank":2,"appreci":2,"love":3,"affirm":1,"look":4,"right":1,"sweet":1,"bye":1,"soon":1,"la":1,"prochain":1,"leav":1,"realli":1,"seriou":1,"sure":1,"name":1,"purpos":1,"mission":1,"no":1,"don":3,"nevermind":2,"exampl":1,"explain":2,"calcul":1,"plu":1,"minu":1,"result":1,"oper":1,"search":3,"internet":2,"googl":3,"wikepedia":1,"definit":1,"find":1,"lookup":1,"joke":1,"funni":1,"laugh":1,"haha":1,"show":2,"sens":1,"humour":1,"login":1,"authent":1,"access":2,"insur":11,"profil":1,"check":6,"statu":9,"claim":23,"chack":1,"progress":4,"case":1,"proce":1,"give":1,"info":1,"current":1,"decis":1,"reach":1,"help":4,"updat":1,"car":6,"accid":5,"onlin":1,"need":6,"monei":5,"immedi":1,"approv":3,"quickli":1,"possibl":2,"new":3,"inform":3,"reject":1,"pend":1,"week":1,"date":1,"gonna":2,"process":5,"provid":2,"call":1,"add":1,"file":6,"damag":2,"want":6,"done":1,"regist":5,"program":1,"creat":1,"fresh":1,"account":4,"becom":1,"custom":1,"pleas":2,"on":2,"member":1,"start":1,"requir":1,"sign":1,"log":1,"user":1,"make":1,"option":2,"hesit":1,"ask":3,"payement":4,"paiement":2,"due":1,"pai":11,"servic":4,"go":3,"transfer":4,"fund":2,"electron":1,"assist":2,"bill":4,"payment":1,"think":1,"cost":3,"plan":1,"accept":1,"paypal":1,"polici":2,"estim":2,"coverag":2,"cover":1,"cancel":1,"exit":1,"backup":1,"back":2,"step":1,"chang":1,"mind":1,"suggest":1,"type":4,"pick":3,"best":2,"deal":1,"situat":1,"subscrib":1,"confirm":1,"subscript":1,"score":1,"analysi":1,"mood":1},"stemmer":{},"lastAdded":0,"events":{"_events":{},"_eventsCount":0}}